pyvents/__init__.py
pyvents/channels.py
pyvents/events.py
pyvents/types.py
pyvents-0.0.1.dist-info/LICENSE
pyvents-0.0.1.dist-info/METADATA
pyvents-0.0.1.dist-info/WHEEL
pyvents-0.0.1.dist-info/RECORD
