Metadata-Version: 2.1
Name: pyvents
Version: 0.0.1
Summary: PyVents is a powerful Python library for events
Home-page: https://github.com/CrazyProger1/PyVents
License: MIT
Author: CrazyProger1
Author-email: crazyproger1@gmail.com
Requires-Python: >=3.12,<4.0
Classifier: License :: OSI Approved :: MIT License
Classifier: Programming Language :: Python :: 3
Classifier: Programming Language :: Python :: 3.12
Project-URL: Documentation, https://github.com/CrazyProger1/PyVents
Project-URL: Repository, https://github.com/CrazyProger1/PyVents
